{
	"info": {
		"_postman_id": "6d393ac2-bc4b-4352-b823-b7b5d0b84681",
		"name": "twitter/posts",
		"schema": "https://schema.getpostman.com/json/collection/v2.1.0/collection.json"
	},
	"item": [
		{
			"name": "localhost:8080/posts",
			"request": {
				"method": "POST",
				"header": [],
				"body": {
					"mode": "raw",
					"raw": "{\r\n    \"post\": \"test post\"\r\n}",
					"options": {
						"raw": {
							"language": "json"
						}
					}
				},
				"url": {
					"raw": "localhost:8080/posts",
					"host": [
						"localhost"
					],
					"port": "8080",
					"path": [
						"posts"
					]
				}
			},
			"response": []
		},
		{
			"name": "localhost:8080/posts/like?postId=1",
			"request": {
				"method": "PUT",
				"header": [],
				"url": {
					"raw": "localhost:8080/posts/like?postId=1",
					"host": [
						"localhost"
					],
					"port": "8080",
					"path": [
						"posts",
						"like"
					],
					"query": [
						{
							"key": "postId",
							"value": "1"
						}
					]
				}
			},
			"response": []
		}
	],
	"protocolProfileBehavior": {}
}